m3u_parser/__init__.py
m3u_parser/exceptions.py
m3u_parser/helper.py
m3u_parser/m3u_parser.py
m3u_parser-0.4.1.dist-info/LICENSE
m3u_parser-0.4.1.dist-info/METADATA
m3u_parser-0.4.1.dist-info/WHEEL
m3u_parser-0.4.1.dist-info/top_level.txt
m3u_parser-0.4.1.dist-info/RECORD
