Metadata-Version: 2.1
Name: m3u-parser
Version: 0.4.1
Summary: A useful package for parsing m3u files or links
Home-page: https://github.com/pawanpaudel93/m3u_parser
Author: Pawan Paudel
Author-email: pawanpaudel93@gmail.com
License: ISC
Classifier: License :: OSI Approved :: ISC License (ISCL)
Classifier: Development Status :: 3 - Alpha
Classifier: Programming Language :: Python :: 3
Classifier: Programming Language :: Python :: 3.6
Classifier: Programming Language :: Python :: 3.7
Classifier: Programming Language :: Python :: 3.8
Classifier: Operating System :: OS Independent
Requires-Python: >=3.0
License-File: LICENSE
Requires-Dist: requests
Requires-Dist: asyncio
Requires-Dist: aiohttp
Requires-Dist: pycountry
